tests/__init__.py
tetris_ballistic/__init__.py
tetris_ballistic/data_analysis_utilities.py
tetris_ballistic/image_loader.py
tetris_ballistic/retrieve_default_configs.py
tetris_ballistic/sweep_parameters.py
tetris_ballistic/tetris_ballistic.py
tetris_ballistic/configs/config_piece_0_combined.yaml
tetris_ballistic/configs/config_piece_0_nonsticky.yaml
tetris_ballistic/configs/config_piece_0_sticky.yaml
tetris_ballistic/configs/config_piece_10_combined.yaml
tetris_ballistic/configs/config_piece_10_nonsticky.yaml
tetris_ballistic/configs/config_piece_10_sticky.yaml
tetris_ballistic/configs/config_piece_11_combined.yaml
tetris_ballistic/configs/config_piece_11_nonsticky.yaml
tetris_ballistic/configs/config_piece_11_sticky.yaml
tetris_ballistic/configs/config_piece_12_combined.yaml
tetris_ballistic/configs/config_piece_12_nonsticky.yaml
tetris_ballistic/configs/config_piece_12_sticky.yaml
tetris_ballistic/configs/config_piece_13_combined.yaml
tetris_ballistic/configs/config_piece_13_nonsticky.yaml
tetris_ballistic/configs/config_piece_13_sticky.yaml
tetris_ballistic/configs/config_piece_14_combined.yaml
tetris_ballistic/configs/config_piece_14_nonsticky.yaml
tetris_ballistic/configs/config_piece_14_sticky.yaml
tetris_ballistic/configs/config_piece_15_combined.yaml
tetris_ballistic/configs/config_piece_15_nonsticky.yaml
tetris_ballistic/configs/config_piece_15_sticky.yaml
tetris_ballistic/configs/config_piece_16_combined.yaml
tetris_ballistic/configs/config_piece_16_nonsticky.yaml
tetris_ballistic/configs/config_piece_16_sticky.yaml
tetris_ballistic/configs/config_piece_17_combined.yaml
tetris_ballistic/configs/config_piece_17_nonsticky.yaml
tetris_ballistic/configs/config_piece_17_sticky.yaml
tetris_ballistic/configs/config_piece_18_combined.yaml
tetris_ballistic/configs/config_piece_18_nonsticky.yaml
tetris_ballistic/configs/config_piece_18_sticky.yaml
tetris_ballistic/configs/config_piece_19_combined.yaml
tetris_ballistic/configs/config_piece_19_nonsticky.yaml
tetris_ballistic-1.2.6.dist-info/LICENSE
tetris_ballistic-1.2.6.dist-info/METADATA
tetris_ballistic-1.2.6.dist-info/WHEEL
tetris_ballistic-1.2.6.dist-info/top_level.txt
tetris_ballistic-1.2.6.dist-info/RECORD
