Metadata-Version: 2.1
Name: tetris-ballistic
Version: 1.2.6
License-File: LICENSE
